[1,["ecpdLyjvZBwrvm+cedCcQy","f0oPvpX5lJs5BZRlk9QlGq","c7rN/2S2xJ8LDDGME2wXbd","27Lp52o25NnJxn65zY2l5L","7dkdXbtcpJDrXVkhimp5te","46jGBUnp1Gm5jsVvvar/Kc","191gUk2NBJy7osFpEqBRiC","85yaF1ZuVPmK0ZVJFXS2UC","92AihvfbVLE5cEyDZyYnDa"],["node","_spriteFrame","_parent","_textureSetter","root","nodeHide","btnSelectAll","selectLayout","nodeBody","data"],[["cc.Node",["_name","_prefab","_contentSize","_components","_trs","_parent","_children","_color"],2,4,5,9,7,1,2,5],["cc.Sprite",["_type","_sizeMode","_enabled","node","_materials","_spriteFrame"],0,1,3,6],["cc.Widget",["_alignFlags","_top","_originalHeight","node"],0,1],["cc.PrefabInfo",["fileId","root"],2,1],["cc.Button",["zoomScale","node","clickEvents"],2,1,9],["cc.Layout",["_resize","_N$layoutType","_N$spacingX","_N$affectedByScale","node","_layoutSize"],-1,1,5],["cc.Label",["_string","_fontSize","_lineHeight","_N$horizontalAlign","_N$verticalAlign","_styleFlags","node","_materials"],-3,1,3],["cc.LabelOutline",["_width","_enabled","node","_color"],1,1,5],["16c65n9CNJDYp8GWOYZ2eZ4",["_fontSize","_lineHeight","_N$horizontalAlign","_N$verticalAlign","_styleFlags","node","_materials"],-2,1,3],"cc.SpriteFrame",["cc.Prefab",["_name"],2],["cc.Node",["_name","_parent","_children","_components","_prefab","_contentSize","_trs"],2,1,2,12,4,5,7],["cbc00KIUBZAwKzkMC0USSZQ",["node","selectLayout","btnSelectAll","nodeHide"],3,1,1,1,1],["cc.ClickEvent",["_componentId","handler","target"],1,1],["d42c4Qr0RpJoKePTNBT0yU/",["node"],3,1],["fcfb0EhBEFHarn2SEpT/rmE",["node","nodeBody"],3,1,1],["5f689QuW7JBwrAD5p0h095g",["node"],3,1],["cc.BlockInputEvents",["node"],3,1],["d5cb20KhElNXY4lhSdeqfOR",["isFixSelfByLayout","spacing","padding","node"],0,1]],[[3,0,1,2],[0,0,5,6,3,1,2,4,2],[0,0,5,3,1,2,4,2],[0,0,6,3,1,2,4,2],[0,0,5,3,1,7,2,4,2],[1,3,4,5,1],[7,0,2,3,2],[2,0,3,2],[13,0,1,2,3],[17,0,1],[7,1,0,2,3,3],[8,0,1,4,2,3,5,6,6],[10,0,2],[0,0,5,3,1,2,2],[0,0,5,1,2,4,2],[11,0,1,2,3,4,5,6,2],[2,0,1,2,3,4],[12,0,1,2,3,1],[3,1,1],[1,0,3,4,5,2],[1,2,1,3,4,5,3],[1,0,1,3,4,5,3],[4,1,2,1],[4,0,1,2,2],[14,0,1],[15,0,1,1],[16,0,1],[5,0,1,2,4,5,4],[5,0,1,2,3,4,5,5],[6,0,1,2,3,4,6,7,6],[6,0,1,2,5,3,4,6,7,7],[8,0,1,2,3,5,6,5],[18,0,1,2,3,4]],[[[{"name":"bg_youxi_xuanze","rect":[0,0,128,56],"offset":[0,0],"originalSize":[128,56],"capInsets":[0,0,0,0]}],[9],0,[0],[3],[1]],[[[12,"SelectGroundFrame"],[3,"SelectGroundFrame",[-7,-8,-9,-10,-11],[[7,45,-2],[17,-6,-5,-4,-3]],[18,-1],[5,720,1280],[360,640,0,0,0,0,1,1,1,1]],[3,"BtnAll",[-15,-16],[[19,1,-12,[15],16],[22,-13,[[8,"cbc00KIUBZAwKzkMC0USSZQ","onBtnSelectAllCard",1]]],[24,-14]],[0,"ec9kkKOrlBt72/LQ3MX/Gh",1],[5,240,104],[0,7.409,0,0,0,0,1,1,1,1]],[3,"DragItem",[-20,-21],[[20,false,0,-17,[6],7],[25,-19,-18]],[0,"0cQgyKAl5A26zzSrL8LUL/",1],[5,200,200],[0,0,0,0,0,0,1,1,1,0]],[1,"Hide",1,[-23,-24],[[16,44,1130,150,-22]],[0,"77nMAKhLRAk7Wb0MjDRWP/",1],[5,720,300],[0,-490,0,0,0,0,1,1,1,1]],[1,"TitlePanel",1,[-27],[[21,1,0,-25,[1],2],[26,-26]],[0,"25fML0SLdKI4zsDJk0cqxw",1],[5,442,85],[0,380.26,0,0,0,0,1,1,1,1]],[15,"List",1,[3],[[-28,[9,-29]],1,4],[0,"5fY6tQaqdBl63yFbaokzDy",1],[5,720,240],[0,153.493,0,0,0,0,1,1,1,1]],[1,"button",3,[-32],[[5,-30,[4],5],[23,0.9,-31,[[8,"cbc00KIUBZAwKzkMC0USSZQ","onSelectItem",1]]]],[0,"2c10O5u9pBv5cQX4TALSw8",1],[5,128,56],[0,-130.466,0,0,0,0,1,1,1,0]],[1,"Btns",1,[2],[[27,1,1,100,-33,[5,240,200]]],[0,"4bsJACQGJAEaK5Pb0UG3lu",1],[5,240,200],[0,-181.746,0,0,0,0,1,1,1,1]],[1,"layout",2,[-35,-36],[[28,1,1,10,true,-34,[5,167.2,40]]],[0,"66wYJT7ZFCPbqoLcd3szeO",1],[5,167.2,40],[0,5,0,0,0,0,1,1,1,1]],[4,"Title",5,[[29,"选择地格",35,35,1,1,-37,[0]],[6,4,-38,[4,4282740127]]],[0,"e7chNC1XVL/piDtltPSZLF",1],[4,4290376700],[5,148,52.1],[0,5.22,0,0,0,0,1,1,1,1]],[13,"New Node",1,[[7,45,-39],[9,-40]],[0,"108F+cTL5DGqo7RotgE+Av",1],[5,720,1280]],[2,"lb",7,[[30,"选择",21,21,1,1,1,-41,[3]],[6,2,-42,[4,4279710542]]],[0,"93uBGOKCpPpZlZ3w9Z075M",1],[5,46,30.46],[0,2.908,0,0,0,0,1,1,1,1]],[4,"Count",4,[[11,20,20,1,1,1,-43,[10]],[10,false,2,-44,[4,4279710542]]],[0,"14hDvj+C5G9Ya3lNYNxSeP",1],[4,4287990118],[5,120,25.2],[0,-22,0,0,0,0,1,1,1,1]],[4,"Count",2,[[31,20,20,1,1,-45,[11]],[10,false,2,-46,[4,4279710542]]],[0,"bdvrUNSkVH0aYXnf4JUHMU",1],[4,4291217094],[5,151.12,25.2],[0,-83.615,0,0,0,0,1,1,1,1]],[2,"Count",9,[[11,32,32,1,1,1,-47,[14]],[6,2,-48,[4,4280632358]]],[0,"28JKAkXiBHpq5LIM6dD8ax",1],[5,100,44.32],[33.6,0,0,0,0,0,1,1,1,1]],[14,"Body",3,[0,"efec5uUvhIL6whLZ0/+SI7",1],[5,200,200],[0,0,0,0,0,0,1,1,1,0]],[32,true,{},{},6],[2,"bg_youxi_yincang",4,[[5,-49,[8],9]],[0,"bd9BAsmBNGKrfYROxh/ZMl",1],[5,110,50],[0,26,0,0,0,0,1,1,1,1]],[2,"video",9,[[5,-50,[12],13]],[0,"9cT7wtFzZNQLbwbi+JMqJk",1],[5,88,62],[-55,0,0,0,0,0,1,0.65,0.65,1]]],0,[0,4,1,0,0,1,0,5,4,0,6,8,0,7,17,0,0,1,0,-1,5,0,-2,11,0,-3,6,0,-4,4,0,-5,8,0,0,2,0,0,2,0,0,2,0,-1,14,0,-2,9,0,0,3,0,8,16,0,0,3,0,-1,16,0,-2,7,0,0,4,0,-1,18,0,-2,13,0,0,5,0,0,5,0,-1,10,0,-1,17,0,0,6,0,0,7,0,0,7,0,-1,12,0,0,8,0,0,9,0,-1,19,0,-2,15,0,0,10,0,0,10,0,0,11,0,0,11,0,0,12,0,0,12,0,0,13,0,0,13,0,0,14,0,0,14,0,0,15,0,0,15,0,0,18,0,0,19,0,9,1,2,2,8,3,2,6,50],[0,0,0,0,0,0,0,0,0,0,0,0,0,0,0,0,0],[-1,-1,1,-1,-1,1,-1,1,-1,1,-1,-1,-1,1,-1,-1,1],[0,0,2,0,0,3,0,4,0,5,0,0,0,6,0,7,8]]]]